delfino_demo/__init__.py
delfino_demo-1.0.1.dist-info/entry_points.txt
delfino_demo-1.0.1.dist-info/WHEEL
delfino_demo-1.0.1.dist-info/METADATA
delfino_demo-1.0.1.dist-info/LICENSE.md
delfino_demo-1.0.1.dist-info/RECORD
